DataPrepKitP/__init__.py
DataPrepKitP-0.1.2.dist-info/LICENCE.txt
DataPrepKitP-0.1.2.dist-info/METADATA
DataPrepKitP-0.1.2.dist-info/WHEEL
DataPrepKitP-0.1.2.dist-info/top_level.txt
DataPrepKitP-0.1.2.dist-info/RECORD
