Metadata-Version: 2.1
Name: DataPrepKitP
Version: 0.1.2
Summary: A Python package for data preparation tasks.
Author: Roqaiah Bin Jamil
Author-email: roqaiahjamil@gmail.com
Classifier: Programming Language :: Python :: 3
Classifier: License :: OSI Approved :: MIT License
Classifier: Operating System :: OS Independent
License-File: LICENCE.txt
Requires-Dist: pandas
Requires-Dist: numpy
